antenny/__init__.py
antenny/api_client.py
antenny/configuration.py
antenny/exceptions.py
antenny/rest.py
antenny/api/__init__.py
antenny/api/client_api.py
antenny/api/events_api.py
antenny/api/registration_api.py
antenny/api/subscription_api.py
antenny/models/__init__.py
antenny/models/client.py
antenny/models/client_list.py
antenny/models/endpoint.py
antenny/models/event.py
antenny/models/event_list.py
antenny/models/header.py
antenny/models/inline_object.py
antenny/models/message.py
antenny/models/new_client.py
antenny/models/new_subscription.py
antenny/models/registration.py
antenny/models/resource.py
antenny/models/subscription.py
antenny/models/subscription_list.py
antenny_py-1.3.0.dist-info/LICENCE
antenny_py-1.3.0.dist-info/METADATA
antenny_py-1.3.0.dist-info/WHEEL
antenny_py-1.3.0.dist-info/top_level.txt
antenny_py-1.3.0.dist-info/RECORD
